README
setup.cfg
setup.py
carpene_discovery/__init__.py
carpene_discovery.egg-info/PKG-INFO
carpene_discovery.egg-info/SOURCES.txt
carpene_discovery.egg-info/dependency_links.txt
carpene_discovery.egg-info/entry_points.txt
carpene_discovery.egg-info/top_level.txt
carpene_discovery.egg-info/zip-safe