Metadata-Version: 1.0
Name: carpene-discovery
Version: 0.1dev
Summary: Python implementation of the Carpene IPv6 host enumeration algorithm
Home-page: carpene.id.au
Author: Clinton Carpene
Author-email: c.carpene@ecu.edu.au
License: GPLv3
Keywords: ipv6 host-discovery carpene-algorithm
Platform: UNKNOWN
